pg_xmat.py
schemas.py
utils.py
pg_xmat-0.3.0.dist-info/licenses/LICENSE
pg_xmat-0.3.0.dist-info/METADATA
pg_xmat-0.3.0.dist-info/WHEEL
pg_xmat-0.3.0.dist-info/entry_points.txt
pg_xmat-0.3.0.dist-info/top_level.txt
pg_xmat-0.3.0.dist-info/RECORD
